cnn_lib/__init__.py
cnn_lib/architectures.py
cnn_lib/cnn_exceptions.py
cnn_lib/data_preparation.py
cnn_lib/detect.py
cnn_lib/flop.py
cnn_lib/lib.py
cnn_lib/random_forest.py
cnn_lib/train.py
cnn_lib/utils.py
cnn_lib/visualization.py
cnn_lib/test/consistency_test.py
cnn_lib-0.9.3.dist-info/licenses/LICENSE
cnn_lib-0.9.3.dist-info/METADATA
cnn_lib-0.9.3.dist-info/WHEEL
cnn_lib-0.9.3.dist-info/top_level.txt
cnn_lib-0.9.3.dist-info/RECORD
