Metadata-Version: 2.4
Name: cnn-lib
Version: 0.9.3
Summary: A package allowing the user to train various CNN architectures and use them for semantic segmentation
Author-email: Ondřej Pešek <pesej.ondrek@gmail.com>
License: MIT
Project-URL: repository, https://github.com/ctu-geoforall-lab/cnn-lib
Requires-Python: >=3.6
License-File: LICENSE
Requires-Dist: numpy
Dynamic: license-file
